MANIFEST.in
README.rst
setup.cfg
setup.py
gearbox_tools.egg-info/PKG-INFO
gearbox_tools.egg-info/SOURCES.txt
gearbox_tools.egg-info/dependency_links.txt
gearbox_tools.egg-info/entry_points.txt
gearbox_tools.egg-info/not-zip-safe
gearbox_tools.egg-info/top_level.txt
gearboxtools/__init__.py
gearboxtools/deploy_circus/__init__.py
gearboxtools/deploy_circus/command.py
gearboxtools/pkgdeps/__init__.py
gearboxtools/pkgdeps/command.py
gearboxtools/tgbootstrap/__init__.py
gearboxtools/tgbootstrap/command.py
gearboxtools/tgbootstrap/template/bootstrap/images/glyphicons-halflings-white.png
gearboxtools/tgbootstrap/template/bootstrap/images/glyphicons-halflings.png
gearboxtools/tgbootstrap/template/bootstrap/javascripts/bootstrap-affix.js
gearboxtools/tgbootstrap/template/bootstrap/javascripts/bootstrap-alert.js
gearboxtools/tgbootstrap/template/bootstrap/javascripts/bootstrap-button.js
gearboxtools/tgbootstrap/template/bootstrap/javascripts/bootstrap-carousel.js
gearboxtools/tgbootstrap/template/bootstrap/javascripts/bootstrap-collapse.js
gearboxtools/tgbootstrap/template/bootstrap/javascripts/bootstrap-dropdown.js
gearboxtools/tgbootstrap/template/bootstrap/javascripts/bootstrap-modal.js
gearboxtools/tgbootstrap/template/bootstrap/javascripts/bootstrap-popover.js
gearboxtools/tgbootstrap/template/bootstrap/javascripts/bootstrap-scrollspy.js
gearboxtools/tgbootstrap/template/bootstrap/javascripts/bootstrap-tab.js
gearboxtools/tgbootstrap/template/bootstrap/javascripts/bootstrap-tooltip.js
gearboxtools/tgbootstrap/template/bootstrap/javascripts/bootstrap-transition.js
gearboxtools/tgbootstrap/template/bootstrap/javascripts/bootstrap-typeahead.js
gearboxtools/tgbootstrap/template/bootstrap/stylesheets/bootstrap-responsive.scss
gearboxtools/tgbootstrap/template/bootstrap/stylesheets/bootstrap.scss
gearboxtools/tgbootstrap/template/bootstrap/stylesheets/bootstrap/_accordion.scss
gearboxtools/tgbootstrap/template/bootstrap/stylesheets/bootstrap/_alerts.scss
gearboxtools/tgbootstrap/template/bootstrap/stylesheets/bootstrap/_breadcrumbs.scss
gearboxtools/tgbootstrap/template/bootstrap/stylesheets/bootstrap/_button-groups.scss
