Metadata-Version: 1.0
Name: gearbox-tools
Version: 0.0.1
Summary: Bunch of utility commands for gearbox toolset
Home-page: https://bitbucket.org/_amol_/gearbox-tools
Author: Alessandro Molina
Author-email: alessandro.molina@axant.it
License: MIT
Keywords: gearbox command-line commands
Platform: UNKNOWN
